{"error":{"name":"TypeError","message":"null is not an object (evaluating 'vm.onLoginTapHandler')","stack":"onLoginTap@file:///app/bundle.js:6538:7\nnotify@file:///app/vendor.js:4423:31\n_emit@file:///app/vendor.js:4440:24\ntap@file:///app/vendor.js:27296:24\nUIApplicationMain@[native code]\n_start@file:///app/vendor.js:4816:26\nrun@file:///app/vendor.js:4844:11\nfile:///app/bundle.js:5059:65\nfile:///app/bundle.js:5075:34\n__webpack_require__@file:///app/runtime.js:751:34\ncheckDeferredModules@file:///app/runtime.js:44:42\nwebpackJsonpCallback@file:///app/runtime.js:31:39\nanonymous@file:///app/bundle.js:2:61\nevaluate@[native code]\nmoduleEvaluation@[native code]\npromiseReactionJob@[native code]"},"deviceData":{"device":{"deviceType":"Phone","deviceModel":"iPhone","deviceOS":"iOS","deviceOSVersion":"12.1","deviceUUID":"1172A8FF-D86D-4306-8CB9-8832E602FF59"},"screen":{"screenHeight":667,"screenWidth":375,"screenScale":2},"appId":"org.nativescript.rpstrackertns","appVersionName":"1.0","appVersionCode":"1.0","runtime":{"name":"nativescript","version":"6.0.1"}},"user":{}}